<Annotations MicronsPerPixel="0.252700">
	<Annotation Id="1" Name="" ReadOnly="0" NameReadOnly="0" LineColorReadOnly="0" Incremental="0" Type="4" LineColor="255" Visible="1" Selected="0" MarkupImagePath="" MacroName="">
		<Attributes>
			<Attribute Name="Epithelial" Id="0" Value=""/>
		</Attributes>
		<Regions>
			<RegionAttributeHeaders>
				<AttributeHeader Id="9999" Name="Region" ColumnWidth="-1"/>
				<AttributeHeader Id="9997" Name="Length" ColumnWidth="-1"/>
				<AttributeHeader Id="9996" Name="Area" ColumnWidth="-1"/>
				<AttributeHeader Id="9998" Name="Text" ColumnWidth="-1"/>
				<AttributeHeader Id="1" Name="Description" ColumnWidth="-1"/>
			</RegionAttributeHeaders>
		</Regions>
		<Plots/>
	</Annotation>
	<Annotation Id="2" Name="" ReadOnly="0" NameReadOnly="0" LineColorReadOnly="0" Incremental="0" Type="4" LineColor="65535" Visible="1" Selected="0" MarkupImagePath="" MacroName="">
		<Attributes>
			<Attribute Name="Lymphocyte" Id="0" Value=""/>
		</Attributes>
		<Regions>
			<RegionAttributeHeaders>
				<AttributeHeader Id="9999" Name="Region" ColumnWidth="-1"/>
				<AttributeHeader Id="9997" Name="Length" ColumnWidth="-1"/>
				<AttributeHeader Id="9996" Name="Area" ColumnWidth="-1"/>
				<AttributeHeader Id="9998" Name="Text" ColumnWidth="-1"/>
				<AttributeHeader Id="1" Name="Description" ColumnWidth="-1"/>
			</RegionAttributeHeaders>
		</Regions>
		<Plots/>
	</Annotation>
	<Annotation Id="3" Name="" ReadOnly="0" NameReadOnly="0" LineColorReadOnly="0" Incremental="0" Type="4" LineColor="16711680" Visible="1" Selected="1" MarkupImagePath="" MacroName="">
		<Attributes>
			<Attribute Name="Neutrophil" Id="0" Value=""/>
		</Attributes>
		<Regions>
			<RegionAttributeHeaders>
				<AttributeHeader Id="9999" Name="Region" ColumnWidth="-1"/>
				<AttributeHeader Id="9997" Name="Length" ColumnWidth="-1"/>
				<AttributeHeader Id="9996" Name="Area" ColumnWidth="-1"/>
				<AttributeHeader Id="9998" Name="Text" ColumnWidth="-1"/>
				<AttributeHeader Id="1" Name="Description" ColumnWidth="-1"/>
			</RegionAttributeHeaders>
			<Region Id="1" Type="0" Zoom="7.358761" Selected="0" ImageLocation="" ImageFocus="-1" Length="105.9" Area="576.5" LengthMicrons="26.8" AreaMicrons="36.8" Text="" NegativeROA="0" InputRegionId="0" Analyze="1" DisplayId="1">
				<Attributes/>
				<Vertices>
					<Vertex X="317" Y="27" Z="0"/>
					<Vertex X="318" Y="27" Z="0"/>
					<Vertex X="318" Y="28" Z="0"/>
					<Vertex X="318" Y="29" Z="0"/>
					<Vertex X="318" Y="30" Z="0"/>
					<Vertex X="319" Y="31" Z="0"/>
					<Vertex X="319" Y="32" Z="0"/>
					<Vertex X="319" Y="33" Z="0"/>
					<Vertex X="319" Y="34" Z="0"/>
					<Vertex X="319" Y="35" Z="0"/>
					<Vertex X="319" Y="36" Z="0"/>
					<Vertex X="319" Y="37" Z="0"/>
					<Vertex X="319" Y="38" Z="0"/>
					<Vertex X="318" Y="38" Z="0"/>
					<Vertex X="318" Y="39" Z="0"/>
					<Vertex X="318" Y="40" Z="0"/>
					<Vertex X="318" Y="41" Z="0"/>
					<Vertex X="317" Y="41" Z="0"/>
					<Vertex X="317" Y="42" Z="0"/>
					<Vertex X="317" Y="43" Z="0"/>
					<Vertex X="316" Y="43" Z="0"/>
					<Vertex X="316" Y="44" Z="0"/>
					<Vertex X="315" Y="44" Z="0"/>
					<Vertex X="315" Y="45" Z="0"/>
					<Vertex X="314" Y="45" Z="0"/>
					<Vertex X="314" Y="46" Z="0"/>
					<Vertex X="313" Y="46" Z="0"/>
					<Vertex X="313" Y="47" Z="0"/>
					<Vertex X="312" Y="47" Z="0"/>
					<Vertex X="312" Y="48" Z="0"/>
					<Vertex X="311" Y="48" Z="0"/>
					<Vertex X="311" Y="49" Z="0"/>
					<Vertex X="310" Y="49" Z="0"/>
					<Vertex X="310" Y="50" Z="0"/>
					<Vertex X="309" Y="50" Z="0"/>
					<Vertex X="308" Y="50" Z="0"/>
					<Vertex X="307" Y="50" Z="0"/>
					<Vertex X="306" Y="50" Z="0"/>
					<Vertex X="305" Y="50" Z="0"/>
					<Vertex X="305" Y="51" Z="0"/>
					<Vertex X="304" Y="51" Z="0"/>
					<Vertex X="304" Y="50" Z="0"/>
					<Vertex X="303" Y="50" Z="0"/>
					<Vertex X="302" Y="50" Z="0"/>
					<Vertex X="301" Y="50" Z="0"/>
					<Vertex X="301" Y="49" Z="0"/>
					<Vertex X="300" Y="49" Z="0"/>
					<Vertex X="300" Y="48" Z="0"/>
					<Vertex X="299" Y="48" Z="0"/>
					<Vertex X="298" Y="47" Z="0"/>
					<Vertex X="298" Y="46" Z="0"/>
					<Vertex X="297" Y="45" Z="0"/>
					<Vertex X="297" Y="44" Z="0"/>
					<Vertex X="296" Y="43" Z="0"/>
					<Vertex X="295" Y="42" Z="0"/>
					<Vertex X="294" Y="41" Z="0"/>
					<Vertex X="294" Y="40" Z="0"/>
					<Vertex X="294" Y="39" Z="0"/>
					<Vertex X="293" Y="39" Z="0"/>
					<Vertex X="293" Y="38" Z="0"/>
					<Vertex X="293" Y="37" Z="0"/>
					<Vertex X="293" Y="36" Z="0"/>
					<Vertex X="293" Y="35" Z="0"/>
					<Vertex X="293" Y="34" Z="0"/>
					<Vertex X="293" Y="33" Z="0"/>
					<Vertex X="293" Y="32" Z="0"/>
					<Vertex X="293" Y="31" Z="0"/>
					<Vertex X="294" Y="31" Z="0"/>
					<Vertex X="294" Y="29" Z="0"/>
					<Vertex X="295" Y="29" Z="0"/>
					<Vertex X="295" Y="28" Z="0"/>
					<Vertex X="295" Y="27" Z="0"/>
					<Vertex X="296" Y="27" Z="0"/>
					<Vertex X="296" Y="26" Z="0"/>
					<Vertex X="297" Y="26" Z="0"/>
					<Vertex X="298" Y="26" Z="0"/>
					<Vertex X="298" Y="25" Z="0"/>
					<Vertex X="299" Y="25" Z="0"/>
					<Vertex X="299" Y="24" Z="0"/>
					<Vertex X="300" Y="24" Z="0"/>
					<Vertex X="301" Y="24" Z="0"/>
					<Vertex X="301" Y="23" Z="0"/>
					<Vertex X="302" Y="23" Z="0"/>
					<Vertex X="303" Y="23" Z="0"/>
					<Vertex X="304" Y="23" Z="0"/>
					<Vertex X="304" Y="22" Z="0"/>
					<Vertex X="305" Y="22" Z="0"/>
					<Vertex X="306" Y="22" Z="0"/>
					<Vertex X="307" Y="22" Z="0"/>
					<Vertex X="308" Y="22" Z="0"/>
					<Vertex X="309" Y="22" Z="0"/>
					<Vertex X="310" Y="22" Z="0"/>
					<Vertex X="311" Y="22" Z="0"/>
					<Vertex X="312" Y="22" Z="0"/>
					<Vertex X="313" Y="23" Z="0"/>
					<Vertex X="314" Y="23" Z="0"/>
					<Vertex X="315" Y="23" Z="0"/>
					<Vertex X="315" Y="24" Z="0"/>
					<Vertex X="316" Y="24" Z="0"/>
					<Vertex X="316" Y="25" Z="0"/>
					<Vertex X="317" Y="25" Z="0"/>
					<Vertex X="317" Y="26" Z="0"/>
					<Vertex X="317" Y="27" Z="0"/>
					<Vertex X="317" Y="27" Z="0"/>
				</Vertices>
			</Region>
			<Region Id="2" Type="0" Zoom="7.358761" Selected="1" ImageLocation="" ImageFocus="-1" Length="111.1" Area="605.5" LengthMicrons="28.1" AreaMicrons="38.7" Text="" NegativeROA="0" InputRegionId="0" Analyze="1" DisplayId="2">
				<Attributes/>
				<Vertices>
					<Vertex X="45" Y="122" Z="0"/>
					<Vertex X="45" Y="123" Z="0"/>
					<Vertex X="45" Y="124" Z="0"/>
					<Vertex X="44" Y="124" Z="0"/>
					<Vertex X="44" Y="125" Z="0"/>
					<Vertex X="43" Y="125" Z="0"/>
					<Vertex X="43" Y="126" Z="0"/>
					<Vertex X="43" Y="127" Z="0"/>
					<Vertex X="42" Y="127" Z="0"/>
					<Vertex X="42" Y="128" Z="0"/>
					<Vertex X="41" Y="128" Z="0"/>
					<Vertex X="40" Y="129" Z="0"/>
					<Vertex X="40" Y="130" Z="0"/>
					<Vertex X="39" Y="130" Z="0"/>
					<Vertex X="38" Y="130" Z="0"/>
					<Vertex X="38" Y="131" Z="0"/>
					<Vertex X="37" Y="131" Z="0"/>
					<Vertex X="36" Y="131" Z="0"/>
					<Vertex X="35" Y="131" Z="0"/>
					<Vertex X="34" Y="131" Z="0"/>
					<Vertex X="33" Y="131" Z="0"/>
					<Vertex X="32" Y="131" Z="0"/>
					<Vertex X="31" Y="131" Z="0"/>
					<Vertex X="30" Y="131" Z="0"/>
					<Vertex X="30" Y="130" Z="0"/>
					<Vertex X="29" Y="130" Z="0"/>
					<Vertex X="28" Y="130" Z="0"/>
					<Vertex X="27" Y="130" Z="0"/>
					<Vertex X="27" Y="129" Z="0"/>
					<Vertex X="26" Y="129" Z="0"/>
					<Vertex X="25" Y="129" Z="0"/>
					<Vertex X="25" Y="128" Z="0"/>
					<Vertex X="25" Y="127" Z="0"/>
					<Vertex X="24" Y="127" Z="0"/>
					<Vertex X="24" Y="126" Z="0"/>
					<Vertex X="23" Y="126" Z="0"/>
					<Vertex X="23" Y="125" Z="0"/>
					<Vertex X="22" Y="125" Z="0"/>
					<Vertex X="22" Y="124" Z="0"/>
					<Vertex X="21" Y="123" Z="0"/>
					<Vertex X="20" Y="122" Z="0"/>
					<Vertex X="20" Y="121" Z="0"/>
					<Vertex X="19" Y="121" Z="0"/>
					<Vertex X="19" Y="120" Z="0"/>
					<Vertex X="19" Y="119" Z="0"/>
					<Vertex X="19" Y="118" Z="0"/>
					<Vertex X="19" Y="117" Z="0"/>
					<Vertex X="19" Y="116" Z="0"/>
					<Vertex X="18" Y="116" Z="0"/>
					<Vertex X="18" Y="115" Z="0"/>
					<Vertex X="18" Y="114" Z="0"/>
					<Vertex X="18" Y="113" Z="0"/>
					<Vertex X="19" Y="113" Z="0"/>
					<Vertex X="19" Y="112" Z="0"/>
					<Vertex X="19" Y="111" Z="0"/>
					<Vertex X="19" Y="110" Z="0"/>
					<Vertex X="20" Y="110" Z="0"/>
					<Vertex X="20" Y="109" Z="0"/>
					<Vertex X="21" Y="109" Z="0"/>
					<Vertex X="21" Y="108" Z="0"/>
					<Vertex X="22" Y="108" Z="0"/>
					<Vertex X="22" Y="107" Z="0"/>
					<Vertex X="23" Y="107" Z="0"/>
					<Vertex X="23" Y="106" Z="0"/>
					<Vertex X="24" Y="106" Z="0"/>
					<Vertex X="24" Y="105" Z="0"/>
					<Vertex X="25" Y="105" Z="0"/>
					<Vertex X="26" Y="105" Z="0"/>
					<Vertex X="26" Y="104" Z="0"/>
					<Vertex X="27" Y="104" Z="0"/>
					<Vertex X="27" Y="103" Z="0"/>
					<Vertex X="28" Y="103" Z="0"/>
					<Vertex X="29" Y="103" Z="0"/>
					<Vertex X="30" Y="103" Z="0"/>
					<Vertex X="30" Y="102" Z="0"/>
					<Vertex X="31" Y="102" Z="0"/>
					<Vertex X="32" Y="102" Z="0"/>
					<Vertex X="33" Y="102" Z="0"/>
					<Vertex X="34" Y="102" Z="0"/>
					<Vertex X="35" Y="102" Z="0"/>
					<Vertex X="36" Y="102" Z="0"/>
					<Vertex X="37" Y="102" Z="0"/>
					<Vertex X="37" Y="103" Z="0"/>
					<Vertex X="38" Y="103" Z="0"/>
					<Vertex X="39" Y="103" Z="0"/>
					<Vertex X="39" Y="104" Z="0"/>
					<Vertex X="40" Y="105" Z="0"/>
					<Vertex X="41" Y="105" Z="0"/>
					<Vertex X="41" Y="106" Z="0"/>
					<Vertex X="42" Y="106" Z="0"/>
					<Vertex X="42" Y="107" Z="0"/>
					<Vertex X="42" Y="108" Z="0"/>
					<Vertex X="43" Y="108" Z="0"/>
					<Vertex X="43" Y="109" Z="0"/>
					<Vertex X="43" Y="110" Z="0"/>
					<Vertex X="44" Y="110" Z="0"/>
					<Vertex X="44" Y="111" Z="0"/>
					<Vertex X="44" Y="112" Z="0"/>
					<Vertex X="44" Y="113" Z="0"/>
					<Vertex X="45" Y="113" Z="0"/>
					<Vertex X="45" Y="114" Z="0"/>
					<Vertex X="45" Y="115" Z="0"/>
					<Vertex X="45" Y="116" Z="0"/>
					<Vertex X="45" Y="117" Z="0"/>
					<Vertex X="45" Y="118" Z="0"/>
					<Vertex X="45" Y="119" Z="0"/>
					<Vertex X="45" Y="120" Z="0"/>
					<Vertex X="44" Y="121" Z="0"/>
					<Vertex X="44" Y="122" Z="0"/>
					<Vertex X="45" Y="122" Z="0"/>
				</Vertices>
			</Region>
		</Regions>
		<Plots/>
	</Annotation>
	<Annotation Id="4" Name="" ReadOnly="0" NameReadOnly="0" LineColorReadOnly="0" Incremental="0" Type="4" LineColor="65280" Visible="1" Selected="0" MarkupImagePath="" MacroName="">
		<Attributes>
			<Attribute Name="Macrophage" Id="0" Value=""/>
		</Attributes>
		<Regions>
			<RegionAttributeHeaders>
				<AttributeHeader Id="9999" Name="Region" ColumnWidth="-1"/>
				<AttributeHeader Id="9997" Name="Length" ColumnWidth="-1"/>
				<AttributeHeader Id="9996" Name="Area" ColumnWidth="-1"/>
				<AttributeHeader Id="9998" Name="Text" ColumnWidth="-1"/>
				<AttributeHeader Id="1" Name="Description" ColumnWidth="-1"/>
			</RegionAttributeHeaders>
		</Regions>
		<Plots/>
	</Annotation>
</Annotations>
